schemachat/__init__.py
schemachat/core/__init__.py
schemachat/core/base_client.py
schemachat/core/base_config.py
schemachat/core/utils.py
schemachat/core/configs/__init__.py
schemachat/core/configs/ollama.py
schemachat/core/configs/openai.py
schemachat/providers/__init__.py
schemachat/providers/factory.py
schemachat/providers/ollama.py
schemachat/providers/openai.py
schemachat-0.1.1.dist-info/METADATA
schemachat-0.1.1.dist-info/WHEEL
schemachat-0.1.1.dist-info/licenses/LICENSE
schemachat-0.1.1.dist-info/RECORD
