Metadata-Version: 2.4
Name: schemachat
Version: 0.1.1
Summary: A unified interface for multiple LLM chat providers with structured output support
Project-URL: Homepage, https://github.com/willysk73/schemachat
Project-URL: Bug Reports, https://github.com/willysk73/schemachat/issues
Project-URL: Source, https://github.com/willysk73/schemachat
Project-URL: Documentation, https://github.com/willysk73/schemachat#readme
Author-email: Will Kang <willysk73@outlook.com>
License-Expression: MIT
License-File: LICENSE
Keywords: ai,chat,language-model,llm,ollama,openai,structured-output
Classifier: Development Status :: 3 - Alpha
Classifier: Intended Audience :: Developers
Classifier: License :: OSI Approved :: MIT License
Classifier: Operating System :: OS Independent
Classifier: Programming Language :: Python :: 3
Classifier: Programming Language :: Python :: 3.10
Classifier: Programming Language :: Python :: 3.11
Classifier: Programming Language :: Python :: 3.12
Classifier: Topic :: Scientific/Engineering :: Artificial Intelligence
Classifier: Topic :: Software Development :: Libraries :: Python Modules
Requires-Python: >=3.10
Requires-Dist: ollama>=0.6.0
Requires-Dist: openai>=2.3.0
Requires-Dist: pydantic>=2.12.0
Requires-Dist: tiktoken>=0.12.0
Provides-Extra: dev
Requires-Dist: black>=23.0.0; extra == 'dev'
Requires-Dist: mypy>=1.5.0; extra == 'dev'
Requires-Dist: pytest>=7.0.0; extra == 'dev'
Requires-Dist: ruff>=0.1.0; extra == 'dev'
